django_generic_json_views-0.7.dist-info/DESCRIPTION.rst
django_generic_json_views-0.7.dist-info/METADATA
django_generic_json_views-0.7.dist-info/RECORD
django_generic_json_views-0.7.dist-info/WHEEL
django_generic_json_views-0.7.dist-info/metadata.json
django_generic_json_views-0.7.dist-info/top_level.txt
django_generic_json_views-0.7.dist-info/zip-safe
json_views/__init__.py
json_views/views.py
