Metadata-Version: 2.0
Name: django-generic-json-views
Version: 0.7
Summary: Class based generic views that render JSON data.
Home-page: https://github.com/bbengfort/django-generic-json-views
Author: Benjamin Bengfort
Author-email: benjamin@bengfort.com
License: Apache
Download-URL: https://github.com/bbengfort/django-generic-json-views/tarball/v0.7
Keywords: django,json,views,generic,class library
Platform: UNKNOWN
Classifier: Framework :: Django
Classifier: Intended Audience :: Developers
Classifier: License :: OSI Approved :: Apache Software License
Classifier: Operating System :: OS Independent
Classifier: Programming Language :: Python
Classifier: Topic :: Internet :: WWW/HTTP
Requires-Dist: Django (>=1.5)
Requires-Dist: six (==1.10.0)
